hyperpocket/__init__.py
hyperpocket/builtin.py
hyperpocket/constants.py
hyperpocket/pocket_auth.py
hyperpocket/pocket_main.py
hyperpocket/prompts.py
hyperpocket/tool_like.py
hyperpocket/auth/README.md
hyperpocket/auth/__init__.py
hyperpocket/auth/context.py
hyperpocket/auth/handler.py
hyperpocket/auth/provider.py
hyperpocket/auth/schema.py
hyperpocket/auth/activeloop/README.md
hyperpocket/auth/activeloop/__init__.py
hyperpocket/auth/activeloop/context.py
hyperpocket/auth/activeloop/token_context.py
hyperpocket/auth/activeloop/token_handler.py
hyperpocket/auth/activeloop/token_schema.py
hyperpocket/auth/adobe/README.md
hyperpocket/auth/adobe/__init__.py
hyperpocket/auth/adobe/context.py
hyperpocket/auth/adobe/token_context.py
hyperpocket/auth/adobe/token_handler.py
hyperpocket/auth/adobe/token_schema.py
hyperpocket/auth/affinity/README.md
hyperpocket/auth/affinity/__init__.py
hyperpocket/auth/affinity/context.py
hyperpocket/auth/affinity/token_context.py
hyperpocket/auth/affinity/token_handler.py
hyperpocket/auth/affinity/token_schema.py
hyperpocket/auth/agentql/README.md
hyperpocket/auth/agentql/__init__.py
hyperpocket/auth/agentql/context.py
hyperpocket/auth/agentql/token_context.py
hyperpocket/auth/agentql/token_handler.py
hyperpocket/auth/agentql/token_schema.py
hyperpocket/auth/ahrefs/README.md
hyperpocket/auth/ahrefs/__init__.py
hyperpocket/auth/ahrefs/context.py
hyperpocket/auth/ahrefs/token_context.py
hyperpocket/auth/ahrefs/token_handler.py
hyperpocket/auth/ahrefs/token_schema.py
hyperpocket/auth/airtable/README.md
hyperpocket/auth/airtable/__init__.py
hyperpocket/auth/airtable/context.py
hyperpocket/auth/airtable/token_context.py
hyperpocket/auth/airtable/token_handler.py
hyperpocket/auth/airtable/token_schema.py
hyperpocket/auth/alchemy/README.md
hyperpocket/auth/alchemy/__init__.py
hyperpocket/auth/alchemy/context.py
hyperpocket/auth/alchemy/token_context.py
hyperpocket/auth/alchemy/token_handler.py
hyperpocket/auth/alchemy/token_schema.py
hyperpocket-0.5.7.dist-info/METADATA
hyperpocket-0.5.7.dist-info/WHEEL
hyperpocket-0.5.7.dist-info/entry_points.txt
hyperpocket-0.5.7.dist-info/RECORD
