Metadata-Version: 2.4
Name: hyperpocket
Version: 0.5.7
Summary: Building AI agent with hyperpocket tool in a flash
Project-URL: Homepage, https://vessl-ai.github.io/hyperpocket
Project-URL: Repository, https://github.com/vessl-ai/hyperpocket
Author-email: Hyperpocket Team <hyperpocket@vessl.ai>
Requires-Python: >=3.10
Requires-Dist: click>=8.1.7
Requires-Dist: cryptography>=44.0.0
Requires-Dist: dynaconf>=3.2.6
Requires-Dist: fastapi>=0.115.5
Requires-Dist: gitpython>=3.1.43
Requires-Dist: httpx==0.28.1
Requires-Dist: jinja2>=3.1.4
Requires-Dist: multiprocess>=0.70.16
Requires-Dist: nest-asyncio>=1.6.0
Requires-Dist: pydantic>=2.10.2
Requires-Dist: pygithub>=2.5.0
Requires-Dist: python-multipart>=0.0.18
Requires-Dist: redis>=5.2.1
Requires-Dist: requests>=2.32.3
Requires-Dist: toml>=0.10.2
Requires-Dist: uvicorn>=0.32.1
Provides-Extra: standard
Requires-Dist: hyperdock-container; extra == 'standard'
